MiniCNN/__init__.py
MiniCNN/main.py
minicnn-0.3.0.dist-info/LICENSE
minicnn-0.3.0.dist-info/METADATA
minicnn-0.3.0.dist-info/WHEEL
minicnn-0.3.0.dist-info/top_level.txt
minicnn-0.3.0.dist-info/RECORD
