Metadata-Version: 2.1
Name: minicnn
Version: 0.3.0
Summary: Minimal, well-documented CNN models for image classification. Great for beginners!
Author: Abhishek Batra
Author-email: abhishek@gmail.com
License: MIT
Requires-Python: >=3.8
License-File: LICENSE
Requires-Dist: torch>=2.0.0
